grapevine/__init__.py
grapevine/adaptation.py
grapevine/grapenuts.py
grapevine/integrator.py
grapevine/util.py
grapevine_mcmc-0.1.0.dist-info/METADATA
grapevine_mcmc-0.1.0.dist-info/WHEEL
grapevine_mcmc-0.1.0.dist-info/RECORD
