Metadata-Version: 2.3
Name: grapevine-mcmc
Version: 0.1.0
Summary: Faster Hamiltonian trajectories for problems with guesses, using Blackjax
Author-email: Teddy Groves <tedgro@dtu.dk>
License: MIT
Requires-Python: >=3.12
Requires-Dist: blackjax>=1.2.4
Requires-Dist: jax==0.4.33
Provides-Extra: demos
Requires-Dist: optimistix>=0.0.8; extra == 'demos'
